ytph/__about__.py
ytph/__init__.py
ytph/address.py
ytph/bic.py
ytph/email.py
ytph/eori.py
ytph/iban.py
ytph/ua.py
ytph/vat.py
ytph/utils/__init__.py
ytph/utils/cache.py
ytph/utils/email.py
ytph-0.0.21.dist-info/METADATA
ytph-0.0.21.dist-info/WHEEL
ytph-0.0.21.dist-info/licenses/LICENSE.txt
ytph-0.0.21.dist-info/RECORD
