Metadata-Version: 2.1
Name: ytph
Version: 0.0.21
Project-URL: Documentation, https://github.com/unknown/ytph#readme
Project-URL: Issues, https://github.com/unknown/ytph/issues
Project-URL: Source, https://github.com/unknown/ytph
Author-email: yanivtoledano <yanivtoledano@gmail.com>
License-Expression: MIT
License-File: LICENSE.txt
Classifier: Development Status :: 4 - Beta
Classifier: Programming Language :: Python
Classifier: Programming Language :: Python :: 3.11
Classifier: Programming Language :: Python :: 3.12
Classifier: Programming Language :: Python :: Implementation :: CPython
Classifier: Programming Language :: Python :: Implementation :: PyPy
Requires-Python: >=3.11
Requires-Dist: email-validator
Requires-Dist: google-i18n-address
Requires-Dist: httpx
Requires-Dist: pydantic
Requires-Dist: schwifty
Requires-Dist: zeep
